AUTHOR
LICENSE
MANIFEST.in
README.rst
setup.py
pypipe/__init__.py
pypipe/configure.py
pypipe/info.py
pypipe/apps/__init__.py
pypipe/apps/main_window.py
pypipe/apps/pypipe_viewer_app.py
pypipe/apps/pypipeview
pypipe/apps/resources/__init__.py
pypipe/apps/resources/add.png
pypipe/apps/resources/change_view.png
pypipe/apps/resources/config.png
pypipe/apps/resources/controller.png
pypipe/apps/resources/delete.png
pypipe/apps/resources/exit.png
pypipe/apps/resources/help.png
pypipe/apps/resources/icones.py
pypipe/apps/resources/inspect.png
pypipe/apps/resources/open.png
pypipe/apps/resources/play.png
pypipe/apps/resources/pypipe.ui
pypipe/apps/resources/search.png
pypipe/apps/resources/transfer.png
pypipe/apps/resources/view.png
pypipe/apps/utils/__init__.py
pypipe/apps/utils/application.py
pypipe/apps/utils/fill_treectrl.py
pypipe/apps/utils/window.py
pypipe/demo/__init__.py
pypipe/gui/__init__.py
pypipe/gui/function_widgets.py
pypipe/gui/plotting.py
pypipe/gui/scroll_widgets.py
pypipe/gui/timered_widgets.py
pypipe/gui/controls/__init__.py
pypipe/gui/controls/directory.py
pypipe/gui/controls/enum.py
pypipe/gui/controls/file.py
pypipe/gui/controls/float.py
pypipe/gui/controls/int.py
pypipe/gui/controls/list.py
pypipe/gui/controls/object.py
pypipe/gui/controls/string.py
pypipe/lib/__init__.py
pypipe/lib/exceptions.py
pypipe/lib/utils.py
pypipe/lib/base/__init__.py
pypipe/lib/base/observable.py
pypipe/lib/base/observable_list.py
pypipe/lib/controls/__init__.py
pypipe/lib/controls/base.py
pypipe/lib/controls/directory.py
pypipe/lib/controls/enum.py
pypipe/lib/controls/file.py
pypipe/lib/controls/float.py
pypipe/lib/controls/int.py
pypipe/lib/controls/list.py
pypipe/lib/controls/object.py
pypipe/lib/controls/string.py
pypipe/test/test_controls.py
pypipe/test/test_decorators.py
python_pypipe.egg-info/PKG-INFO
python_pypipe.egg-info/SOURCES.txt
python_pypipe.egg-info/dependency_links.txt
python_pypipe.egg-info/requires.txt
python_pypipe.egg-info/top_level.txt