Metadata-Version: 1.1
Name: python-pypipe
Version: 0.0.1
Summary: 
